Workbook

Sheet Финансовая модель
A1: VIBE42 — Финансовая модель проекта обучения
A3: ВХОДНЫЕ ДАННЫЕ
A4: Параметр | B4: Значение | C4: Ед. изм.
A5: Стоимость обучения за 1 участника | B5: 100000 | C5: тг
A6: Количество участников в месяц | B6: 250 | C6: чел.
A7: Количество инженеров | B7: 25 | C7: чел.
A8: Максимальная оплата инженера | B8: 100000 | C8: тг
A9: Оклад руководителя проекта | B9: 500000 | C9: тг
A10: Процент руководителя от выручки | B10: 0.03 | C10: %
A11: Максимальная зарплата руководителя | B11: 1200000 | C11: тг
A13: РАСЧЁТЫ
A14: Показатель | B14: Сумма | C14: Комментарий
A15: Общая выручка | B15: =B5*B6 -> 25000000 | C15: цена × участники
A16: ФОТ инженеров | B16: =B7*B8 -> 2500000 | C16: инженеры × ставка
A17: Доля ФОТ инженеров от выручки | B17: =IF(B15=0,0,B16/B15) -> 0.1 | C17: ФОТ / выручка
A18: Бонус руководителя | B18: =B15*B10 -> 750000 | C18: выручка × %
A19: Расчётный доход руководителя | B19: =B9+B18 -> 1250000 | C19: оклад + бонус
A20: Фактическая выплата руководителю | B20: =MIN(B19,B11) -> 1200000 | C20: ограничен лимитом
A21: Остаток (прибыль проекта) | B21: =B15-B16-B20 -> 21300000 | C21: выручка − ФОТ − рук.
A22: Рентабельность проекта | B22: =IF(B15=0,0,(B15-B16-B20)/B15) -> 0.852 | C22: прибыль / выручка
A24: КЛЮЧЕВЫЕ ПОКАЗАТЕЛИ ЭФФЕКТИВНОСТИ
A25: Показатель | B25: Значение | C25: На 1 участника
A26: Выручка | B26: =B15 -> 25000000 | C26: =IF(B6=0,0,B15/B6) -> 100000
A27: ФОТ инженеров | B27: =B16 -> 2500000 | C27: =IF(B6=0,0,B16/B6) -> 10000
A28: Выплата руководителю | B28: =B20 -> 1200000 | C28: =IF(B6=0,0,B20/B6) -> 4800
A29: Прибыль проекта | B29: =B21 -> 21300000 | C29: =IF(B6=0,0,B21/B6) -> 85200
A30: Рентабельность (%) | B30: =B22 -> 0.852 | C30: —
A32: * Синий цвет — входные данные (изменяемые). Чёрный — расчётные формулы. Все значения в тенге (тг).

Sheet Сценарии
A1: VIBE42 — Сценарный анализ
A3: ПАРАМЕТРЫ (связаны с листом «Финансовая модель»)
A4: Стоимость обучения (тг) | B4: ='Финансовая модель'!B5 -> 100000
A5: Макс. оплата инженера (тг) | B5: ='Финансовая модель'!B8 -> 100000
A6: Оклад руководителя (тг) | B6: ='Финансовая модель'!B9 -> 500000
A7: % руководителя от выручки | B7: ='Финансовая модель'!B10 -> 0.03
A8: Макс. зарплата руководителя (тг) | B8: ='Финансовая модель'!B11 -> 1200000
A10: СЦЕНАРНЫЙ АНАЛИЗ
A11: Участников | B11: Выручка (тг) | C11: ФОТ инженеров (тг) | D11: Доход руководителя (тг) | E11: Прибыль проекта (тг) | F11: Рентабельность
A12: 150 | B12: =A12*B4 -> 15000000 | C12: =CEILING(A12/10,1)*MIN(B4,B5) -> 1500000 | D12: =MIN(B6+B12*B7,B8) -> 950000 | E12: =B12-C12-D12 -> 12550000 | F12: =IF(B12=0,0,E12/B12) -> 0.83666667
A13: 200 | B13: =A13*B4 -> 20000000 | C13: =CEILING(A13/10,1)*MIN(B4,B5) -> 2000000 | D13: =MIN(B6+B13*B7,B8) -> 1100000 | E13: =B13-C13-D13 -> 16900000 | F13: =IF(B13=0,0,E13/B13) -> 0.845
A14: 250 | B14: =A14*B4 -> 25000000 | C14: =CEILING(A14/10,1)*MIN(B4,B5) -> 2500000 | D14: =MIN(B6+B14*B7,B8) -> 1200000 | E14: =B14-C14-D14 -> 21300000 | F14: =IF(B14=0,0,E14/B14) -> 0.852
A15: 300 | B15: =A15*B4 -> 30000000 | C15: =CEILING(A15/10,1)*MIN(B4,B5) -> 3000000 | D15: =MIN(B6+B15*B7,B8) -> 1200000 | E15: =B15-C15-D15 -> 25800000 | F15: =IF(B15=0,0,E15/B15) -> 0.86
A16: 400 | B16: =A16*B4 -> 40000000 | C16: =CEILING(A16/10,1)*MIN(B4,B5) -> 4000000 | D16: =MIN(B6+B16*B7,B8) -> 1200000 | E16: =B16-C16-D16 -> 34800000 | F16: =IF(B16=0,0,E16/B16) -> 0.87
A18: ИТОГОВЫЕ ПОКАЗАТЕЛИ (базовый сценарий — 250 участников)
A19: Показатель | B19: Значение (тг / %)
A20: Выручка | B20: =B14 -> 25000000
A21: ФОТ инженеров | B21: =C14 -> 2500000
A22: Выплата руководителю | B22: =D14 -> 1200000
A23: Прибыль проекта | B23: =E14 -> 21300000
A24: Рентабельность | B24: =F14 -> 0.852
A26: * Зелёный цвет — значения, связанные с листом «Финансовая модель». Чёрный — расчётные формулы. Синий — изменяемые входные данные.
